pyood/OutlierDetector.py
pyood/__init__.py
pyood-0.2.1.data/scripts/OutlierDetector.py
pyood-0.2.1.dist-info/LICENSE
pyood-0.2.1.dist-info/METADATA
pyood-0.2.1.dist-info/WHEEL
pyood-0.2.1.dist-info/top_level.txt
pyood-0.2.1.dist-info/RECORD
