Metadata-Version: 2.1
Name: pyood
Version: 0.2.1
Summary: Detect outliers of sequence in stream.
Home-page: https://github.com/SamanFekri/StreamOutlierDetector
Author: Saman Fekri
Author-email: samanf74@gmail.com
License: UNKNOWN
Platform: UNKNOWN
Classifier: Programming Language :: Python :: 3
Classifier: Programming Language :: Python :: 3.4
Classifier: Programming Language :: Python :: 3.5
Classifier: Programming Language :: Python :: 3.6
Classifier: Programming Language :: Python :: 3.7
Classifier: License :: OSI Approved :: GNU Affero General Public License v3 or later (AGPLv3+)
Classifier: Operating System :: OS Independent
